compressem/__init__.py
compressem/decoder.py
compressem/encoder.py
compress_em-0.1.dist-info/METADATA
compress_em-0.1.dist-info/WHEEL
compress_em-0.1.dist-info/top_level.txt
compress_em-0.1.dist-info/RECORD
